[{"prefecture_jis_code":"26","city_jis_code":"26106","zip_code":"6008146","prefecture_name_kana":"ｷﾖｳﾄﾌ","city_name_kana":"ｷﾖｳﾄｼｼﾓｷﾞﾖｳｸ","town_name_kana":"ｻﾞｲﾓｸﾁﾖｳ","prefecture_name":"京都府","city_name":"京都市下京区","town_name":"る、河原町通七条下る、七条通間之町西入、七条通間之町東入、七条通河原町西"},{"prefecture_jis_code":"26","city_jis_code":"26106","zip_code":"6008146","prefecture_name_kana":"ｷﾖｳﾄﾌ","city_name_kana":"ｷﾖｳﾄｼｼﾓｷﾞﾖｳｸ","town_name_kana":"ｻﾞｲﾓｸﾁﾖｳ","prefecture_name":"京都府","city_name":"京都市下京区","town_name":"上る、東洞院通七条下る、柳馬場通七条上る）"},{"prefecture_jis_code":"26","city_jis_code":"26106","zip_code":"6008146","prefecture_name_kana":"ｷﾖｳﾄﾌ","city_name_kana":"ｷﾖｳﾄｼｼﾓｷﾞﾖｳｸ","town_name_kana":"ｻﾞｲﾓｸﾁﾖｳ","prefecture_name":"京都府","city_name":"京都市下京区","town_name":"入、七条通河原町東入、七条通高倉西入、七条通高倉東入、七条通土手町"},{"prefecture_jis_code":"26","city_jis_code":"26106","zip_code":"6008146","prefecture_name_kana":"ｷﾖｳﾄﾌ","city_name_kana":"ｷﾖｳﾄｼｼﾓｷﾞﾖｳｸ","town_name_kana":"ｻﾞｲﾓｸﾁﾖｳ","prefecture_name":"京都府","city_name":"京都市下京区","town_name":"材木町（間之町通七条下る、間之町通七条上る、河原町通七条上"},{"prefecture_jis_code":"26","city_jis_code":"26106","zip_code":"6008146","prefecture_name_kana":"ｷﾖｳﾄﾌ","city_name_kana":"ｷﾖｳﾄｼｼﾓｷﾞﾖｳｸ","town_name_kana":"ｻﾞｲﾓｸﾁﾖｳ","prefecture_name":"京都府","city_name":"京都市下京区","town_name":"西入、七条通東洞院東入、高倉通七条上る、高倉通七条下る、土手町通七条"}]