[{"prefecture_jis_code":"23","city_jis_code":"23207","zip_code":"4410312","prefecture_name_kana":"ｱｲﾁｹﾝ","city_name_kana":"ﾄﾖｶﾜｼ","town_name_kana":"ﾐﾄﾁﾖｳﾆｼｶﾞﾀ","prefecture_name":"愛知県","city_name":"豊川市","town_name":"御津町西方"},{"prefecture_jis_code":"23","city_jis_code":"23207","zip_code":"4410312","prefecture_name_kana":"ｱｲﾁｹﾝ","city_name_kana":"ﾄﾖｶﾜｼ","town_name_kana":"ﾐﾄﾁﾖｳﾆｼｶﾞﾀｱｹﾞﾊﾏ","prefecture_name":"愛知県","city_name":"豊川市","town_name":"御津町西方揚浜"},{"prefecture_jis_code":"23","city_jis_code":"23207","zip_code":"4410312","prefecture_name_kana":"ｱｲﾁｹﾝ","city_name_kana":"ﾄﾖｶﾜｼ","town_name_kana":"ﾐﾄﾁﾖｳﾆｼｶﾞﾀｲﾘﾊﾏ","prefecture_name":"愛知県","city_name":"豊川市","town_name":"御津町西方入浜"},{"prefecture_jis_code":"23","city_jis_code":"23207","zip_code":"4410312","prefecture_name_kana":"ｱｲﾁｹﾝ","city_name_kana":"ﾄﾖｶﾜｼ","town_name_kana":"ﾐﾄﾁﾖｳﾆｼｶﾞﾀｲﾘﾖｳﾀﾞ","prefecture_name":"愛知県","city_name":"豊川市","town_name":"御津町西方井領田"},{"prefecture_jis_code":"23","city_jis_code":"23207","zip_code":"4410312","prefecture_name_kana":"ｱｲﾁｹﾝ","city_name_kana":"ﾄﾖｶﾜｼ","town_name_kana":"ﾐﾄﾁﾖｳﾆｼｶﾞﾀｷﾂﾈﾂﾞｶ","prefecture_name":"愛知県","city_name":"豊川市","town_name":"御津町西方狐塚"},{"prefecture_jis_code":"23","city_jis_code":"23207","zip_code":"4410312","prefecture_name_kana":"ｱｲﾁｹﾝ","city_name_kana":"ﾄﾖｶﾜｼ","town_name_kana":"ﾐﾄﾁﾖｳﾆｼｶﾞﾀｸｻｸ","prefecture_name":"愛知県","city_name":"豊川市","town_name":"御津町西方九策"},{"prefecture_jis_code":"23","city_jis_code":"23207","zip_code":"4410312","prefecture_name_kana":"ｱｲﾁｹﾝ","city_name_kana":"ﾄﾖｶﾜｼ","town_name_kana":"ﾐﾄﾁﾖｳﾆｼｶﾞﾀｹﾞﾝﾉｳ","prefecture_name":"愛知県","city_name":"豊川市","town_name":"御津町西方源農"},{"prefecture_jis_code":"23","city_jis_code":"23207","zip_code":"4410312","prefecture_name_kana":"ｱｲﾁｹﾝ","city_name_kana":"ﾄﾖｶﾜｼ","town_name_kana":"ﾐﾄﾁﾖｳﾆｼｶﾞﾀｺｶﾞｲﾂ","prefecture_name":"愛知県","city_name":"豊川市","town_name":"御津町西方小貝津"},{"prefecture_jis_code":"23","city_jis_code":"23207","zip_code":"4410312","prefecture_name_kana":"ｱｲﾁｹﾝ","city_name_kana":"ﾄﾖｶﾜｼ","town_name_kana":"ﾐﾄﾁﾖｳﾆｼｶﾞﾀｼﾓﾊﾏﾐﾁ","prefecture_name":"愛知県","city_name":"豊川市","town_name":"御津町西方下浜道"},{"prefecture_jis_code":"23","city_jis_code":"23207","zip_code":"4410312","prefecture_name_kana":"ｱｲﾁｹﾝ","city_name_kana":"ﾄﾖｶﾜｼ","town_name_kana":"ﾐﾄﾁﾖｳﾆｼｶﾞﾀｼﾞﾖｳﾉｸﾁ","prefecture_name":"愛知県","city_name":"豊川市","town_name":"御津町西方常ノ口"},{"prefecture_jis_code":"23","city_jis_code":"23207","zip_code":"4410312","prefecture_name_kana":"ｱｲﾁｹﾝ","city_name_kana":"ﾄﾖｶﾜｼ","town_name_kana":"ﾐﾄﾁﾖｳﾆｼｶﾞﾀﾁﾖｳﾀﾞ","prefecture_name":"愛知県","city_name":"豊川市","town_name":"御津町西方長田"},{"prefecture_jis_code":"23","city_jis_code":"23207","zip_code":"4410312","prefecture_name_kana":"ｱｲﾁｹﾝ","city_name_kana":"ﾄﾖｶﾜｼ","town_name_kana":"ﾐﾄﾁﾖｳﾆｼｶﾞﾀﾄｲﾀﾞ","prefecture_name":"愛知県","city_name":"豊川市","town_name":"御津町西方樋田"},{"prefecture_jis_code":"23","city_jis_code":"23207","zip_code":"4410312","prefecture_name_kana":"ｱｲﾁｹﾝ","city_name_kana":"ﾄﾖｶﾜｼ","town_name_kana":"ﾐﾄﾁﾖｳﾆｼｶﾞﾀﾅｶﾐﾁ","prefecture_name":"愛知県","city_name":"豊川市","town_name":"御津町西方中道"},{"prefecture_jis_code":"23","city_jis_code":"23207","zip_code":"4410312","prefecture_name_kana":"ｱｲﾁｹﾝ","city_name_kana":"ﾄﾖｶﾜｼ","town_name_kana":"ﾐﾄﾁﾖｳﾆｼｶﾞﾀﾅｶﾔｼｷ","prefecture_name":"愛知県","city_name":"豊川市","town_name":"御津町西方中屋敷"},{"prefecture_jis_code":"23","city_jis_code":"23207","zip_code":"4410312","prefecture_name_kana":"ｱｲﾁｹﾝ","city_name_kana":"ﾄﾖｶﾜｼ","town_name_kana":"ﾐﾄﾁﾖｳﾆｼｶﾞﾀﾅｼﾉ","prefecture_name":"愛知県","city_name":"豊川市","town_name":"御津町西方梨野"},{"prefecture_jis_code":"23","city_jis_code":"23207","zip_code":"4410312","prefecture_name_kana":"ｱｲﾁｹﾝ","city_name_kana":"ﾄﾖｶﾜｼ","town_name_kana":"ﾐﾄﾁﾖｳﾆｼｶﾞﾀﾊﾏﾀﾞ","prefecture_name":"愛知県","city_name":"豊川市","town_name":"御津町西方浜田"},{"prefecture_jis_code":"23","city_jis_code":"23207","zip_code":"4410312","prefecture_name_kana":"ｱｲﾁｹﾝ","city_name_kana":"ﾄﾖｶﾜｼ","town_name_kana":"ﾐﾄﾁﾖｳﾆｼｶﾞﾀﾋｸﾞﾗｼ","prefecture_name":"愛知県","city_name":"豊川市","town_name":"御津町西方日暮"},{"prefecture_jis_code":"23","city_jis_code":"23207","zip_code":"4410312","prefecture_name_kana":"ｱｲﾁｹﾝ","city_name_kana":"ﾄﾖｶﾜｼ","town_name_kana":"ﾐﾄﾁﾖｳﾆｼｶﾞﾀﾋﾛﾀ","prefecture_name":"愛知県","city_name":"豊川市","town_name":"御津町西方広田"},{"prefecture_jis_code":"23","city_jis_code":"23207","zip_code":"4410312","prefecture_name_kana":"ｱｲﾁｹﾝ","city_name_kana":"ﾄﾖｶﾜｼ","town_name_kana":"ﾐﾄﾁﾖｳﾆｼｶﾞﾀﾏﾂﾓﾄ","prefecture_name":"愛知県","city_name":"豊川市","town_name":"御津町西方松本"},{"prefecture_jis_code":"23","city_jis_code":"23207","zip_code":"4410312","prefecture_name_kana":"ｱｲﾁｹﾝ","city_name_kana":"ﾄﾖｶﾜｼ","town_name_kana":"ﾐﾄﾁﾖｳﾆｼｶﾞﾀﾐﾔﾅｶﾞ","prefecture_name":"愛知県","city_name":"豊川市","town_name":"御津町西方宮長"}]