[{"prefecture_jis_code":"16","city_jis_code":"16343","zip_code":"9380162","prefecture_name_kana":"ﾄﾔﾏｹﾝ","city_name_kana":"ｼﾓﾆｲｶﾜｸﾞﾝｱｻﾋﾏﾁ","town_name_kana":"ﾔﾏｻﾞｷ","prefecture_name":"富山県","city_name":"下新川郡朝日町","town_name":"山崎"},{"prefecture_jis_code":"16","city_jis_code":"16343","zip_code":"9380162","prefecture_name_kana":"ﾄﾔﾏｹﾝ","city_name_kana":"ｼﾓﾆｲｶﾜｸﾞﾝｱｻﾋﾏﾁ","town_name_kana":"ﾔﾏｻﾞｷ(ｲﾜｻｷ)","prefecture_name":"富山県","city_name":"下新川郡朝日町","town_name":"山崎（岩崎）"},{"prefecture_jis_code":"16","city_jis_code":"16343","zip_code":"9380162","prefecture_name_kana":"ﾄﾔﾏｹﾝ","city_name_kana":"ｼﾓﾆｲｶﾜｸﾞﾝｱｻﾋﾏﾁ","town_name_kana":"ﾔﾏｻﾞｷ(ｺｻﾞｲｹ)","prefecture_name":"富山県","city_name":"下新川郡朝日町","town_name":"山崎（小在池）"},{"prefecture_jis_code":"16","city_jis_code":"16343","zip_code":"9380162","prefecture_name_kana":"ﾄﾔﾏｹﾝ","city_name_kana":"ｼﾓﾆｲｶﾜｸﾞﾝｱｻﾋﾏﾁ","town_name_kana":"ﾔﾏｻﾞｷ(ｺｼ)","prefecture_name":"富山県","city_name":"下新川郡朝日町","town_name":"山崎（越）"},{"prefecture_jis_code":"16","city_jis_code":"16343","zip_code":"9380162","prefecture_name_kana":"ﾄﾔﾏｹﾝ","city_name_kana":"ｼﾓﾆｲｶﾜｸﾞﾝｱｻﾋﾏﾁ","town_name_kana":"ﾔﾏｻﾞｷ(ﾂｼﾞ)","prefecture_name":"富山県","city_name":"下新川郡朝日町","town_name":"山崎（辻）"},{"prefecture_jis_code":"16","city_jis_code":"16343","zip_code":"9380162","prefecture_name_kana":"ﾄﾔﾏｹﾝ","city_name_kana":"ｼﾓﾆｲｶﾜｸﾞﾝｱｻﾋﾏﾁ","town_name_kana":"ﾔﾏｻﾞｷ(ﾊﾅﾌｻ)","prefecture_name":"富山県","city_name":"下新川郡朝日町","town_name":"山崎（花房）"},{"prefecture_jis_code":"16","city_jis_code":"16343","zip_code":"9380162","prefecture_name_kana":"ﾄﾔﾏｹﾝ","city_name_kana":"ｼﾓﾆｲｶﾜｸﾞﾝｱｻﾋﾏﾁ","town_name_kana":"ﾔﾏｻﾞｷ(ﾊﾆﾕｳ)","prefecture_name":"富山県","city_name":"下新川郡朝日町","town_name":"山崎（羽入）"},{"prefecture_jis_code":"16","city_jis_code":"16343","zip_code":"9380162","prefecture_name_kana":"ﾄﾔﾏｹﾝ","city_name_kana":"ｼﾓﾆｲｶﾜｸﾞﾝｱｻﾋﾏﾁ","town_name_kana":"ﾔﾏｻﾞｷ(ﾎﾞｳ)","prefecture_name":"富山県","city_name":"下新川郡朝日町","town_name":"山崎（坊）"}]