[{"prefecture_jis_code":"03","city_jis_code":"03210","town_name_kana":"ｲｶﾆｹｲｻｲｶﾞﾅｲﾊﾞｱｲ","town_name":"以下に掲載がない場合","zip_code":"0292200"},{"prefecture_jis_code":"03","city_jis_code":"03210","town_name_kana":"ｵﾄﾓﾁﾖｳ","town_name":"小友町","zip_code":"0292207"},{"prefecture_jis_code":"03","city_jis_code":"03210","town_name_kana":"ｹｾﾝﾁﾖｳ","town_name":"気仙町","zip_code":"0292204"},{"prefecture_jis_code":"03","city_jis_code":"03210","town_name_kana":"ﾀｶﾀﾁﾖｳ","town_name":"高田町","zip_code":"0292205"},{"prefecture_jis_code":"03","city_jis_code":"03210","town_name_kana":"ﾀｹｺﾏﾁﾖｳ","town_name":"竹駒町","zip_code":"0292203"},{"prefecture_jis_code":"03","city_jis_code":"03210","town_name_kana":"ﾋﾛﾀﾁﾖｳ","town_name":"広田町","zip_code":"0292208"},{"prefecture_jis_code":"03","city_jis_code":"03210","town_name_kana":"ﾔﾊｷﾞﾁﾖｳ","town_name":"矢作町","zip_code":"0292201"},{"prefecture_jis_code":"03","city_jis_code":"03210","town_name_kana":"ﾖｺﾀﾁﾖｳ","town_name":"横田町","zip_code":"0292202"},{"prefecture_jis_code":"03","city_jis_code":"03210","town_name_kana":"ﾖﾈｻｷﾁﾖｳ","town_name":"米崎町","zip_code":"0292206"}]