[{"prefecture_jis_code":"26","city_jis_code":"26104","zip_code":"6048214","prefecture_name_kana":"ｷﾖｳﾄﾌ","city_name_kana":"ｷﾖｳﾄｼﾅｶｷﾞﾖｳｸ","town_name_kana":"ﾑｶﾃﾞﾔﾁﾖｳ","prefecture_name":"京都府","city_name":"京都市中京区","town_name":"百足屋町（新町通蛸薬師下る、新町通錦小路上る、蛸薬師通新町西入、錦小路"},{"prefecture_jis_code":"26","city_jis_code":"26104","zip_code":"6048214","prefecture_name_kana":"ｷﾖｳﾄﾌ","city_name_kana":"ｷﾖｳﾄｼﾅｶｷﾞﾖｳｸ","town_name_kana":"ﾑｶﾃﾞﾔﾁﾖｳ","prefecture_name":"京都府","city_name":"京都市中京区","town_name":"通新町西入、錦小路通新町東入）"}]